LICENSE
README.md
setup.py
enterpath/__init__.py
enterpath/enterpath.py
enterpath.egg-info/PKG-INFO
enterpath.egg-info/SOURCES.txt
enterpath.egg-info/dependency_links.txt
enterpath.egg-info/entry_points.txt
enterpath.egg-info/top_level.txt